ubindex/__init__.py
ubindex/authorize.py
ubindex/base.py
ubindex/dataapi.py
ubindex/vars.py
ubindex-0.1.2.dist-info/DESCRIPTION.rst
ubindex-0.1.2.dist-info/METADATA
ubindex-0.1.2.dist-info/RECORD
ubindex-0.1.2.dist-info/WHEEL
ubindex-0.1.2.dist-info/metadata.json
ubindex-0.1.2.dist-info/top_level.txt
